ngmapi/__init__.py
ngmapi/__main__.py
ngmapi/app.py
ngmapi/func.py
ngmapi-0.1.55.dist-info/METADATA
ngmapi-0.1.55.dist-info/WHEEL
ngmapi-0.1.55.dist-info/entry_points.txt
ngmapi-0.1.55.dist-info/top_level.txt
ngmapi-0.1.55.dist-info/RECORD
