Metadata-Version: 2.1
Name: ngmapi
Version: 0.1.55
Summary: Just a demo project
Project-URL: Homepage, https://github.com/ngmaibulat/training-flask
Project-URL: Documentation, https://github.com/ngmaibulat/training-flask
Project-URL: Changes, https://github.com/ngmaibulat/training-flask
Keywords: flask,project
Requires-Python: >=3.10
Requires-Dist: Flask
Requires-Dist: Jinja2
Requires-Dist: MarkupSafe
